petriflow/__init__.py
petriflow/xml_classes.py
petriflow/xml_subclasses.py
resources/hypouver.xml
resources/missing_type_hypouver.xml
resources/new_model.xml
resources/petriflow.schema.wrong.xsd
resources/petriflow.schema.xsd
resources/wrong_initials_hypouver.xml
tests/__init__.py
tests/xml_classes_tests.py
petriflowLibrary-1.0.1.dist-info/METADATA
petriflowLibrary-1.0.1.dist-info/WHEEL
petriflowLibrary-1.0.1.dist-info/top_level.txt
petriflowLibrary-1.0.1.dist-info/RECORD
