Metadata-Version: 2.1
Name: petriflowLibrary
Version: 1.0.1
Summary: Import/Export library
Author: Peter Kopecký
Author-email: xkopecky@stuba.sk
Classifier: Intended Audience :: Developers
Classifier: Programming Language :: Python
Classifier: Programming Language :: Python :: 3
Classifier: Programming Language :: Python :: 3.6
Classifier: Programming Language :: Python :: 3.7
Classifier: Programming Language :: Python :: 3.8
Classifier: Programming Language :: Python :: 3.9
Classifier: Programming Language :: Python :: 3.10
Classifier: Programming Language :: Python :: 3.11
Classifier: Operating System :: OS Independent
Requires-Dist: setuptools (~=65.6.3)
Requires-Dist: six (~=1.16.0)
Requires-Dist: lxml (~=4.9.1)
Requires-Dist: chardet (~=5.1.0)
